sharesphere/admin.py
sharesphere/app.py
sharesphere/auth.py
sharesphere/cli.py
sharesphere/config.py
sharesphere/config.yaml
sharesphere/database.py
sharesphere/file_manager.py
sharesphere/models.py
sharesphere-1.0.2.dist-info/LICENSE
sharesphere-1.0.2.dist-info/METADATA
sharesphere-1.0.2.dist-info/WHEEL
sharesphere-1.0.2.dist-info/entry_points.txt
sharesphere-1.0.2.dist-info/RECORD
