Metadata-Version: 2.3
Name: sharesphere
Version: 1.0.2
Summary: A multi-user file sharing system built with Streamlit, SQLAlchemy, and SQLite.
License: MIT
Author: Rakesh
Author-email: rakeshpandey820@gmail.com
Requires-Python: >=3.10,<=3.13
Classifier: License :: OSI Approved :: MIT License
Classifier: Programming Language :: Python :: 3
Classifier: Programming Language :: Python :: 3.10
Classifier: Programming Language :: Python :: 3.11
Classifier: Programming Language :: Python :: 3.12
Classifier: Programming Language :: Python :: 3.13
Requires-Dist: SQLAlchemy (>=2.0.37,<3.0.0)
Requires-Dist: bcrypt (>=4.2.1,<5.0.0)
Requires-Dist: click (>=8.1.8,<9.0.0)
Requires-Dist: omegaconf (>=2.3.0,<3.0.0)
Requires-Dist: streamlit (>=1.41.1,<2.0.0)
